{"status": "ok", "data": {"aqi": 50, "idx": 6741, "attributions": [{"url": "http://www.euskadi.eus/gobierno-vasco/medio-ambiente/", "name": "Departamento de Medio Ambiente, Planificaci\u00f3n Territorial y Vivienda \u00b7 Gobierno Vasco", "logo": "Spain-GobiernoVasco.png"}, {"url": "https://waqi.info/", "name": "World Air Quality Index Project"}], "city": {"geo": [43.333011997426, -3.0425600003492], "name": "Santurce, Santurtzi, Pa\u00eds Vasco, Spain", "url": "https://aqicn.org/city/spain/pais-vasco/santurtzi/santurce", "location": ""}, "dominentpol": "pm25", "iaqi": {"co": {"v": 0.1}, "h": {"v": 78.6}, "no2": {"v": 15.6}, "o3": {"v": 22.8}, "p": {"v": 1017.1}, "pm10": {"v": 21}, "pm25": {"v": 50}, "so2": {"v": 2.6}, "t": {"v": 19.4}, "w": {"v": 2}, "wg": {"v": 6.3}}, "time": {"s": "2022-05-19 16:00:00", "tz": "+02:00", "v": 1652976000, "iso": "2022-05-19T16:00:00+02:00"}, "forecast": {"daily": {"o3": [{"avg": 24, "day": "2022-05-19", "max": 33, "min": 17}, {"avg": 25, "day": "2022-05-20", "max": 34, "min": 17}, {"avg": 24, "day": "2022-05-21", "max": 35, "min": 17}, {"avg": 25, "day": "2022-05-22", "max": 37, "min": 13}, {"avg": 37, "day": "2022-05-23", "max": 37, "min": 34}], "pm10": [{"avg": 13, "day": "2022-05-19", "max": 18, "min": 10}, {"avg": 14, "day": "2022-05-20", "max": 17, "min": 10}, {"avg": 17, "day": "2022-05-21", "max": 21, "min": 14}, {"avg": 36, "day": "2022-05-22", "max": 60, "min": 25}, {"avg": 25, "day": "2022-05-23", "max": 25, "min": 17}], "pm25": [{"avg": 39, "day": "2022-05-19", "max": 52, "min": 26}, {"avg": 39, "day": "2022-05-20", "max": 51, "min": 25}, {"avg": 49, "day": "2022-05-21", "max": 57, "min": 36}, {"avg": 66, "day": "2022-05-22", "max": 75, "min": 57}, {"avg": 51, "day": "2022-05-23", "max": 51, "min": 44}], "uvi": [{"avg": 1, "day": "2022-05-19", "max": 7, "min": 0}, {"avg": 1, "day": "2022-05-20", "max": 7, "min": 0}, {"avg": 1, "day": "2022-05-21", "max": 5, "min": 0}, {"avg": 1, "day": "2022-05-22", "max": 4, "min": 0}, {"avg": 1, "day": "2022-05-23", "max": 5, "min": 0}, {"avg": 0, "day": "2022-05-24", "max": 0, "min": 0}]}}, "debug": {"sync": "2022-05-20T02:43:15+09:00"}}}