{"status": "ok", "data": {"aqi": 24, "idx": 6708, "attributions": [{"url": "http://www.eea.europa.eu/themes/air/", "name": "European Environment Agency", "logo": "Europe-EEA.png"}, {"url": "https://medioambiente.asturias.es/", "name": "Monitorizaci\u00f3n Red de Calidad del Aire del Principado de Asturias", "logo": "Spain-Asturias.png"}, {"url": "https://waqi.info/", "name": "World Air Quality Index Project"}], "city": {"geo": [43.3440389, -5.9737246], "name": "Trubia, Asturias, Spain", "url": "https://aqicn.org/city/spain/asturias/trubia", "location": ""}, "dominentpol": "o3", "iaqi": {"co": {"v": 0.1}, "h": {"v": 93.2}, "no2": {"v": 4.4}, "o3": {"v": 24.4}, "p": {"v": 1020.1}, "pm10": {"v": 19}, "pm25": {"v": 30}, "so2": {"v": 1.6}, "t": {"v": 14.8}, "w": {"v": 6}, "wg": {"v": 12}}, "time": {"s": "2022-05-12 16:00:00", "tz": "+02:00", "v": 1652371200, "iso": "2022-05-12T16:00:00+02:00"}, "forecast": {"daily": {"o3": [{"avg": 22, "day": "2022-05-12", "max": 29, "min": 15}, {"avg": 25, "day": "2022-05-13", "max": 33, "min": 21}, {"avg": 23, "day": "2022-05-14", "max": 31, "min": 13}, {"avg": 24, "day": "2022-05-15", "max": 34, "min": 17}, {"avg": 27, "day": "2022-05-16", "max": 27, "min": 21}], "pm10": [{"avg": 12, "day": "2022-05-12", "max": 23, "min": 9}, {"avg": 9, "day": "2022-05-13", "max": 12, "min": 7}, {"avg": 17, "day": "2022-05-14", "max": 21, "min": 13}, {"avg": 15, "day": "2022-05-15", "max": 21, "min": 11}, {"avg": 10, "day": "2022-05-16", "max": 11, "min": 10}], "pm25": [{"avg": 43, "day": "2022-05-12", "max": 65, "min": 30}, {"avg": 32, "day": "2022-05-13", "max": 38, "min": 25}, {"avg": 53, "day": "2022-05-14", "max": 59, "min": 42}, {"avg": 44, "day": "2022-05-15", "max": 62, "min": 31}, {"avg": 32, "day": "2022-05-16", "max": 40, "min": 32}], "uvi": [{"avg": 0, "day": "2022-05-12", "max": 3, "min": 0}, {"avg": 1, "day": "2022-05-13", "max": 5, "min": 0}, {"avg": 1, "day": "2022-05-14", "max": 6, "min": 0}, {"avg": 1, "day": "2022-05-15", "max": 5, "min": 0}, {"avg": 1, "day": "2022-05-16", "max": 4, "min": 0}, {"avg": 0, "day": "2022-05-17", "max": 0, "min": 0}]}}, "debug": {"sync": "2022-05-13T00:11:10+09:00"}}}